Metadata-Version: 2.1
Name: CharEncoding
Version: 0.0.2
Summary: Character Encoding Algorithms
Home-page: https://github.com/rishabhc9
Author: Rishabh Chopda
Author-email: aaditchopda2@gmail.com
License: MIT
Keywords: Encoding,7-Segment Display,ASCII85 Encoding,ASCII Code,Aztec Barcode,Base-32 Crockford,Base32,Base45,Base 58,Base62,Base64,Base91,Baudot,Binary,Chuck Norris Unary Code,EBCDIC Encoding,French Postal Barcode,Gray Code,Morse Code,BCD Encoding,Excess-3 Code (Stibitz),Resistor Value
Classifier: Development Status :: 5 - Production/Stable
Classifier: Intended Audience :: Education
Classifier: Operating System :: OS Independent
Classifier: License :: OSI Approved :: MIT License
Classifier: Programming Language :: Python :: 3
License-File: LICENSE.txt
